emulation/__init__.py
emulation/__version__.py
emulation-0.1.0.dist-info/licenses/LICENSE
emulation-0.1.0.dist-info/METADATA
emulation-0.1.0.dist-info/WHEEL
emulation-0.1.0.dist-info/top_level.txt
emulation-0.1.0.dist-info/RECORD
